{
    "name" : "xmlfile-apps",
    "connectorRef" : {
        "bundleName" : "org.forgerock.openicf.connectors.file.openicf-xml-connector",
        "bundleVersion" : "1.1.0.0",
        "connectorName" : "com.forgerock.openicf.xml.XMLConnector"
    },
    "producerBufferSize" : 100,
    "connectorPoolingSupported" : true,
    "poolConfigOption" : {
        "maxObjects" : 10,
        "maxIdle" : 10,
        "maxWait" : 150000,
        "minEvictableIdleTimeMillis" : 120000,
        "minIdle" : 1
    },
    "operationTimeout" : {
        "CREATE" : -1,
        "TEST" : -1,
        "AUTHENTICATE" : -1,
        "SEARCH" : -1,
        "VALIDATE" : -1,
        "GET" : -1,
        "UPDATE" : -1,
        "DELETE" : -1,
        "SCRIPT_ON_CONNECTOR" : -1,
        "SCRIPT_ON_RESOURCE" : -1,
        "SYNC" : -1,
        "SCHEMA" : -1
    },
    "configurationProperties" : {
        "xsdIcfFilePath" : "samples/sample0/data/resource-schema-1.xsd",
        "xsdFilePath" : "samples/sample0/data/resource-schema-extension.xsd",
        "xmlFilePath" : "samples/sample0/data/xmlConnectorDataApps.xml"
    },
    "objectTypes" : {
        "application" : {
            "$schema" : "http://json-schema.org/draft-03/schema",
            "id" : "__APPLICATION__",
            "type" : "object",
            "nativeType" : "__APPLICATION__",
            "properties" : {
                "_id" : {
                    "type" : "string",
                    "nativeName" : "__UID__"
                },
                "description" : {
                    "type" : "string",
                    "nativeName" : "description",
                    "nativeType" : "string"
                },
                "name" : {
                    "type" : "string",
                    "required" : true,
                    "nativeName" : "__NAME__",
                    "nativeType" : "string"
                },
                "iconPath" : {
                    "type" : "string",
                    "nativeName" : "iconPath",
                    "nativeType" : "string"
                },
                "isDefault" : {
                    "type" : "boolean",
                    "nativeName" : "isDefault",
                    "nativeType" : "boolean"
                },
                "needsApproval" : {
                    "type" : "boolean",
                    "nativeName" : "needsApproval",
                    "nativeType" : "boolean"
                }
            }
        }
    },
    "operationOptions" : {
    }
}